Workbook

Sheet Funcional
B1: Criterio | C1: Respuesta/Indicador | D1: Máximo de puntos a evaluar | E1: NAE | F1: WAVENET | G1: ORACLE | H1: HITSS | I1: BLIPBLIP | J1: LARAIGO | K1: FONYOU | L1: SIXBELL | M1: PRONÓSTICA
B2: Integrarse con WhatsApp 1 línea Claro te ayuda para técnicos y otra línea de clientes para interactuar con las siguientes funcionalidades: *Línea autorizada para atención técnicos: # WhatsApp para atención y soporte a técnicos Casos razonamiento (impedimentos OT) *Validar técnico activo e inicio conversación (Código SAP· OTP): Validar en SSFF y OFSC si el técnico está disponible para dar acceso al canal de servicio. *Perfilamiento para menú/Submenú: Identificar técnico (planta int., planta ext.) y desplegar menú adecuado *Consulta datos OT/ servicios y materiales: Consulta tipo OT, cliente, equipos, manuales requeridos. *Cambiar estados en OFSC: OT: Iniciada, completada, reprogramada y/o cancelada. | C2: No Cumple (0 puntos) Cumple parcialmente (+1 punto) Cumple totalmente (+1 punto) | D2: 2 | E2: 2 | F2: 2 | G2: 2 | H2: 1 | I2: 2 | J2: 2 | K2: 2 | L2: 2 | M2: 2
B3: ¿La solución permite resolver el caso de uso? *Validar ubicación técnico- Comunicación cliente antes inicio OT: Conectarse a plataformas como Waze/ Maps para notificar al cliente tiempo de llegada técnico. Técnico en sitio, datos técnico y servicio. Calcular distancia entre el técnico y el predio. Si está dentro de perímetro inicia OT. | C3: No Cumple (0 puntos) Cumple parcialmente (+1 punto) Cumple totalmente (+1 punto) | D3: 2 | E3: 2 | F3: 2 | G3: 1 | H3: 2 | I3: 1 | J3: 2 | K3: 2 | L3: 2 | M3: 2
B4: ¿La solución permite resolver el caso de uso? *Razonar para inicio OT, reportar incidente: Se comunica con el técnico a la línea de Whatsapp Claro te ayuda (Ya existe) para analizar notas- audios técnico: cliente no contesta, peligroso, lloviendo OT errónea y mantiene la conversación, permisos de administración y problemas plataformas de red. | C4: No Cumple (0 puntos) Cumple parcialmente (+1 punto) Cumple totalmente (+1 punto) | D4: 2 | E4: 2 | F4: 2 | G4: 2 | H4: 2 | I4: 2 | J4: 2 | K4: 2 | L4: 2 | M4: 2
B5: ¿La solución permite resolver el caso de uso? *Modulación comunicación cliente no contesta: Dispara y recibe respuestas de la línea del Whatsapp del cliente, confirma visita, cancela o solicita reprogramar para informar al técnico como continuar. | C5: No Cumple (0 puntos) Cumple parcialmente (+1 punto) Cumple totalmente (+1 punto) | D5: 2 | E5: 2 | F5: 2 | G5: 2 | H5: 2 | I5: 1 | J5: 2 | K5: 2 | L5: 2 | M5: 1
B6: ¿El sistema puede escalar fácilmente en nuevos casos de uso? Entregar estimación de alto nivel para evolutivos: Diagnóstico con Xpertrak – OT iniciada (Home Integrity y pathtrack) y/o plataformas FTTH: Extraer datos cuenta matricial, servicio, equipos, analizarlos e informar fallas. | C6: No Cumple (0 puntos) Cumple parcialmente (+1 punto) Cumple totalmente (+1 punto) | D6: 2 | E6: 1 | F6: 0 | G6: 1 | H6: 1 | I6: 0 | J6: 1 | K6: 1 | L6: 0 | M6: 0
B7: ¿El sistema puede escalar fácilmente en nuevos casos de uso? Entregar estimación de alto nivel para evolutivos: Optimización inventario y ficha materiales: Análisis de los materiales por tipo OT según consumo reportado por los técnicos, sugerir la cantidad de material necesario por data recolectada. Informar CPEs necesarios para la ejecución orden de trabajo. Sugerir elementos de apoyo como escaleras, hombre tercer apoyo, andamios, etc... | C7: No Cumple (0 puntos) Cumple parcialmente (+1 punto) Cumple totalmente (+1 punto) | D7: 2 | E7: 1 | F7: 0 | G7: 2 | H7: 1 | I7: 0 | J7: 1 | K7: 1 | L7: 0 | M7: 0
B8: ¿El sistema puede escalar fácilmente en nuevos casos de uso? Entregar estimación de alto nivel para evolutivos: Asignación inteligente siguiente OT: Según experiencia del técnico, distancia entre sitios y duración de la visita para optimizar rutas y tiempos. Permisos de administración (horarios laborables, requisitos de instalación (parafiscales cuando sean necesarios). | C8: No Cumple (0 puntos) Cumple parcialmente (+1 punto) Cumple totalmente (+1 punto) | D8: 2 | E8: 2 | F8: 1 | G8: 2 | H8: 2 | I8: 0 | J8: 2 | K8: 2 | L8: 0 | M8: 0
B9: ¿El sistema puede escalar fácilmente en nuevos casos de uso? Entregar estimación de alto nivel para evolutivos: Gestión OT para todos los segmentos, Consulta alarmas y notas no estructuradas (ITSM) a interpretar para diagnosticar falla y notificar al técnico acciones a realizar. Casos atípicos. | C9: No Cumple (0 puntos) Cumple parcialmente (+1 punto) Cumple totalmente (+1 punto) | D9: 2 | E9: 2 | F9: 1 | G9: 2 | H9: 1 | I9: 1 | J9: 0 | K9: 1 | L9: 1 | M9: 1
B10: ¿El sistema puede escalar fácilmente en nuevos casos de uso? Entregar estimación de alto nivel para evolutivos: Validar estado zona afectada - fija, Consulta dirección(es) y cuenta(s) afectada(s) y vecino (s) para HFC y FTTH. Tener en cuenta histórico de reportes. | C10: No Cumple (0 puntos) Cumple parcialmente (+1 punto) Cumple totalmente (+1 punto) | D10: 2 | E10: 2 | F10: 0 | G10: 2 | H10: 2 | I10: 1 | J10: 2 | K10: 1 | L10: 0 | M10: 0
B11: ¿El sistema puede escalar fácilmente en nuevos casos de uso? Entregar estimación de alto nivel para evolutivos: Diagnóstico Xpertrak – fija (prioritario), Consulta gráfica(s) del analizador de espectro sobre nodos RPHY y HFC tomando una imagen en tiempo real de gráfica para dar respuesta. | C11: No Cumple (0 puntos) Cumple parcialmente (+1 punto) Cumple totalmente (+1 punto) | D11: 2 | E11: 2 | F11: 0 | G11: 2 | H11: 1 | I11: 0 | J11: 0 | K11: 1 | L11: 0 | M11: 0
C12: Total puntos | D12: =SUM(D2:D11) -> 20 | E12: =SUM(E2:E11) -> 18 | F12: =SUM(F2:F11) -> 10 | G12: =SUM(G2:G11) -> 18 | H12: =SUM(H2:H11) -> 15 | I12: =SUM(I2:I11) -> 8 | J12: =SUM(J2:J11) -> 14 | K12: =SUM(K2:K11) -> 15 | ... M12: =SUM(M2:M11) -> 8
C13: Ponderado escala | D13: =D12/5 -> 4 | E13: {=_xlfn.IFS(E12=0,0,E12<4,1,E12<8,2,E12<12,3,E12<16,4,E12<=20,5)} -> 5 | F13: {=_xlfn.IFS(F12=0,0,F12<4,1,F12<8,2,F12<12,3,F12<16,4,F12<=20,5)} -> 3 | G13: {=_xlfn.IFS(G12=0,0,G12<4,1,G12<8,2,G12<12,3,G12<16,4,G12<=20,5)} -> 5 | H13: {=_xlfn.IFS(H12=0,0,H12<4,1,H12<8,2,H12<12,3,H12<16,4,H12<=20,5)} -> 4 | I13: {=_xlfn.IFS(I12=0,0,I12<4,1,I12<8,2,I12<12,3,I12<16,4,I12<=20,5)} -> 3 | J13: {=_xlfn.IFS(J12=0,0,J12<4,1,J12<8,2,J12<12,3,J12<16,4,J12<=20,5)} -> 4 | K13: {=_xlfn.IFS(K12=0,0,K12<4,1,K12<8,2,K12<12,3,K12<16,4,K12<=20,5)} -> 4 | L13: {=_xlfn.IFS(L12=0,0,L12<4,1,L12<8,2,L12<12,3,L12<16,4,L12<=20,5)} -> 3 | M13: {=_xlfn.IFS(M12=0,0,M12<4,1,M12<8,2,M12<12,3,M12<16,4,M12<=20,5)} -> 3

Sheet Técnico
B1: Criterio | C1: Respuesta/Indicador | D1: Máximo de puntos a evaluar | E1: NAE | F1: WAVENET | G1: ORACLE | H1: HITSS | I1: BLIPBLIP | J1: LARAIGO | K1: FONYOU | L1: SIXBELL | M1: PRONÓSTICA
B2: ¿Utiliza modelos de IA adecuados para el caso de uso (generativa, predictiva, etc.)? | C2: No Cumple (0 puntos) Cumple parcialmente (+1 punto) Cumple totalmente (+1 punto) | D2: 2 | E2: 2 | F2: 2 | G2: 2 | H2: 2 | I2: 1 | J2: 2 | K2: 0 | L2: 2 | M2: 2
B3: ¿Permite el entrenamiento con datos propios y ajustes mediante retroalimentación? | C3: No Cumple (0 puntos) Cumple parcialmente (+1 punto) Cumple totalmente (+1 punto) | D3: 2 | E3: 2 | F3: 2 | G3: 2 | H3: 2 | I3: 1 | J3: 2 | K3: 0 | L3: 2 | M3: 2
B4: ¿Puede personalizarse sin necesidad de conocimientos técnicos avanzados? | C4: No Cumple (0 puntos) Cumple parcialmente (+1 punto) Cumple totalmente (+1 punto) | D4: 2 | E4: 1 | F4: 0 | G4: 1 | H4: 0 | I4: 0 | J4: 2 | K4: 1 | L4: 1 | M4: 0
B5: ¿Incluye herramientas para monitorear precisión, latencia y desempeño del modelo? | C5: No Cumple (0 puntos) Cumple parcialmente (+1 punto) Cumple totalmente (+1 punto) | D5: 2 | E5: 2 | F5: 2 | G5: 2 | H5: 2 | I5: 1 | J5: 0 | K5: 2 | L5: 2 | M5: 2
B6: ¿Es independiente de un proveedor cloud específico o permite portabilidad? | C6: No Cumple (0 puntos) Cumple parcialmente (+1 punto) Cumple totalmente (+1 punto) | D6: 2 | E6: 1 | F6: 2 | G6: 1 | H6: 2 | I6: 1 | J6: 1 | K6: 1 | L6: 1 | M6: 1
B7: ¿Soporta operación multicanal y multitenant con configuración separada? | C7: No Cumple (0 puntos) Cumple parcialmente (+1 punto) Cumple totalmente (+1 punto) | D7: 2 | E7: 2 | F7: 0 | G7: 1 | H7: 2 | I7: 0 | J7: 0 | K7: 1 | L7: 2 | M7: 2
B8: ¿Tiene mecanismos para detectar sesgos o auditar decisiones automatizadas? | C8: No Cumple (0 puntos) Cumple parcialmente (+1 punto) Cumple totalmente (+1 punto) | D8: 2 | E8: 1 | F8: 2 | G8: 1 | H8: 1 | I8: 0 | J8: 0 | K8: 2 | L8: 2 | M8: 0
B9: ¿Es escalable ante incrementos de carga, volumenes de datos y usuarios concurrentes? | C9: No Cumple (0 puntos) Cumple parcialmente (+1 punto) Cumple totalmente (+1 punto) | D9: 2 | E9: 1 | F9: 1 | G9: 2 | H9: 1 | I9: 0 | J9: 1 | K9: 1 | L9: 0 | M9: 2
B10: ¿Implementa gobernanza técnica para trazabilidad y control del ciclo de vida del modelo? | C10: No Cumple (0 puntos) Cumple parcialmente (+1 punto) Cumple totalmente (+1 punto) | D10: 2 | E10: 2 | F10: 0 | G10: 2 | H10: 2 | I10: 0 | J10: 1 | K10: 0 | L10: 2 | M10: 0
B11: ¿Permite, capacidades analíticas filtrado, extracción de metadata, análisis automatizado, análisis predictivo, análisis de causas raíz, detección de malas prácticas y análisis en tiempo real,? | C11: No Cumple (0 puntos) Cumple parcialmente (+1 punto) Cumple totalmente (+1 punto) | D11: 2 | E11: 0 | F11: 2 | G11: 2 | H11: 2 | I11: 0 | J11: 0 | K11: 0 | L11: 2 | M11: 2
B12: Puede procesar y correlacionar texto, imágenes, tablas y escenarios para generar insights de negocio. | C12: No Cumple (0 puntos) Cumple parcialmente (+1 punto) Cumple totalmente (+1 punto) | D12: 2 | E12: 0 | F12: 0 | G12: 2 | H12: 0 | I12: 1 | J12: 2 | K12: 0 | L12: 1 | M12: 1
B13: Soporta la ingestión y análisis de datos de diversas fuentes, incluyendo documentos escaneados (OCR). | C13: No Cumple (0 puntos) Cumple parcialmente (+1 punto) Cumple totalmente (+1 punto) | D13: 2 | E13: 0 | F13: 0 | G13: 1 | H13: 1 | I13: 0 | J13: 1 | K13: 0 | L13: 1 | M13: 0
... B29: ¿El proveedor detalla el plan de soporte 7x24 que incluya niveles de escalamiento, SLA por tipo de incidente y personas? | C29: No Cumple (0 puntos) Cumple parcialmente (+1 punto) Cumple totalmente (+1 punto) | D29: 2 | E29: 2 | F29: 2 | G29: 2 | H29: 1 | I29: 0 | J29: 2 | K29: 2 | L29: 2 | M29: 2
C30: Total puntos | D30: =SUM(D2:D29) -> 56 | E30: =SUM(E2:E29) -> 37 | F30: =SUM(F2:F29) -> 25 | G30: =SUM(G2:G29) -> 49 | H30: =SUM(H2:H29) -> 34 | I30: =SUM(I2:I29) -> 12 | J30: =SUM(J2:J29) -> 25 | K30: =SUM(K2:K29) -> 18 | ... M30: =SUM(M2:M29) -> 29
C31: Ponderado escala | D31: =D30/5 -> 11.2 | E31: {=_xlfn.IFS(E30=0,0,E30<12,1,E30<24,2,E30<38,3,E30<48,4,E30<=60,5)} -> 3 | F31: {=_xlfn.IFS(F30=0,0,F30<12,1,F30<24,2,F30<36,3,F30<48,4,F30<=60,5)} -> 3 | G31: {=_xlfn.IFS(G30=0,0,G30<12,1,G30<24,2,G30<36,3,G30<48,4,G30<=60,5)} -> 5 | H31: {=_xlfn.IFS(H30=0,0,H30<12,1,H30<24,2,H30<36,3,H30<48,4,H30<=60,5)} -> 3 | I31: {=_xlfn.IFS(I30=0,0,I30<12,1,I30<24,2,I30<36,3,I30<48,4,I30<=60,5)} -> 2 | J31: {=_xlfn.IFS(J30=0,0,J30<12,1,J30<24,2,J30<36,3,J30<48,4,J30<=60,5)} -> 3 | K31: {=_xlfn.IFS(K30=0,0,K30<12,1,K30<24,2,K30<36,3,K30<48,4,K30<=60,5)} -> 2 | L31: {=_xlfn.IFS(L30=0,0,L30<12,1,L30<24,2,L30<36,3,L30<48,4,L30<=60,5)} -> 4 | M31: {=_xlfn.IFS(M30=0,0,M30<12,1,M30<24,2,M30<36,3,M30<48,4,M30<=60,5)} -> 3

Sheet Arqui1
B1: Criterio | C1: Respuesta/Indicador | D1: Máximo de puntos a evaluar | E1: NAE | F1: WAVENET | G1: ORACLE | H1: HITSS | I1: BLIPBLIP | J1: LARAIGO | K1: FONYOU | L1: SIXBELL
B2: Descripción de solución ajustada al negocio y experiencia en este tipo de proyectos | C2: No Cumple (0 puntos) Cumple parcialmente (+1 punto) Cumple totalmente (+1 punto) | D2: 2 | E2: 2 | F2: 2 | G2: 2 | H2: 2 | I2: 2 | J2: 2 | K2: 2 | L2: 2
B3: Diagrama y arquitectura lógica entre solución y arquitectura conceptual del Operador | C3: No Cumple (0 puntos) Cumple parcialmente (+1 punto) Cumple totalmente (+1 punto) | D3: 2 | E3: 2 | F3: 2 | G3: 2 | H3: 2 | I3: 2 | J3: 2 | K3: 2 | L3: 2
B4: Explicación arquitectura, hardware/software, TO-BE y transición | C4: No Cumple (0 puntos) Cumple parcialmente (+1 punto) Cumple totalmente (+1 punto) | D4: 2 | E4: 2 | F4: 2 | G4: 1 | H4: 2 | I4: 2 | J4: 2 | K4: 2 | L4: 2
B5: Arquitectura modular y desacoplada | C5: No Cumple (0 puntos) Cumple parcialmente (+1 punto) Cumple totalmente (+1 punto) | D5: 2 | E5: 2 | F5: 2 | G5: 1 | H5: 2 | I5: 2 | J5: 2 | K5: 2 | L5: 2
B6: Diagrama de integración de red y documento para revisión área redes Claro | C6: No Cumple (0 puntos) Cumple parcialmente (+1 punto) Cumple totalmente (+1 punto) | D6: 2 | E6: 2 | F6: 2 | G6: 1 | H6: 2 | I6: 2 | J6: 1 | K6: 2 | L6: 2
B7: Soporte local y/o regional | C7: No Cumple (0 puntos) Cumple parcialmente (+1 punto) Cumple totalmente (+1 punto) | D7: 2 | E7: 2 | F7: 2 | G7: 2 | H7: 2 | I7: 2 | J7: 2 | K7: 2 | L7: 2
B8: Implementaciones exitosas en operadores de telecomunicaciones | C8: No Cumple (0 puntos) Cumple parcialmente (+1 punto) Cumple totalmente (+1 punto) | D8: 2 | E8: 2 | F8: 2 | G8: 1 | H8: 2 | I8: 2 | J8: 2 | K8: 2 | L8: 2
B9: Referencias de operadores y volúmenes manejados | C9: No Cumple (0 puntos) Cumple parcialmente (+1 punto) Cumple totalmente (+1 punto) | D9: 2 | E9: 1 | F9: 1 | G9: 2 | H9: 1 | I9: 1 | J9: 1 | K9: 1 | L9: 1
B10: Certificaciones ISO, CMMI u otras | C10: No Cumple (0 puntos) Cumple parcialmente (+1 punto) Cumple totalmente (+1 punto) | D10: 2 | E10: 2 | F10: 2 | G10: 2 | H10: 1 | I10: 1 | J10: 2 | K10: 1 | L10: 1
B11: Metodología de desarrollo con altos estándares | C11: No Cumple (0 puntos) Cumple parcialmente (+1 punto) Cumple totalmente (+1 punto) | D11: 2 | E11: 2 | F11: 2 | G11: 2 | H11: 2 | I11: 2 | J11: 2 | K11: 2 | L11: 2
B12: Confidencialidad de información | C12: No Cumple (0 puntos) Cumple parcialmente (+1 punto) Cumple totalmente (+1 punto) | D12: 2 | E12: 2 | F12: 2 | G12: 2 | H12: 2 | I12: 2 | J12: 2 | K12: 2 | L12: 2
B13: Plan de proyecto detallado y milestones | C13: No Cumple (0 puntos) Cumple parcialmente (+1 punto) Cumple totalmente (+1 punto) | D13: 2 | E13: 2 | F13: 2 | G13: 2 | H13: 2 | I13: 2 | J13: 2 | K13: 2 | L13: 2
... B16: Anexo técnico que soporte las respuestas | C16: No Cumple (0 puntos) Cumple parcialmente (+1 punto) Cumple totalmente (+1 punto) | D16: 2 | E16: 2 | F16: 2 | G16: 1 | H16: 2 | I16: 2 | J16: 2 | K16: 2 | L16: 2
C17: Total puntos | D17: =SUM(D2:D16) -> 30 | E17: =SUM(E2:E16) -> 29 | F17: =SUM(F2:F16) -> 29 | G17: =SUM(G2:G16) -> 24 | H17: =SUM(H2:H16) -> 28 | I17: =SUM(I2:I16) -> 28 | J17: =SUM(J2:J16) -> 28 | K17: =SUM(K2:K16) -> 27 | L17: =SUM(L2:L16) -> 28
C18: Ponderado escala | D18: =D17/5 -> 6 | E18: {=_xlfn.IFS(E17<6,1,E17<12,2,E17<18,3,E17<24,4,E17<=30,5)} -> 5 | F18: {=_xlfn.IFS(F17<6,1,F17<12,2,F17<18,3,F17<24,4,F17<=30,5)} -> 5 | G18: {=_xlfn.IFS(G17<6,1,G17<12,2,G17<18,3,G17<24,4,G17<=30,5)} -> 5 | H18: {=_xlfn.IFS(H17<6,1,H17<12,2,H17<18,3,H17<24,4,H17<=30,5)} -> 5 | I18: {=_xlfn.IFS(I17<6,1,I17<12,2,I17<18,3,I17<24,4,I17<=30,5)} -> 5 | J18: {=_xlfn.IFS(J17<6,1,J17<12,2,J17<18,3,J17<24,4,J17<=30,5)} -> 5 | K18: {=_xlfn.IFS(K17<6,1,K17<12,2,K17<18,3,K17<24,4,K17<=30,5)} -> 5 | L18: {=_xlfn.IFS(L17<6,1,L17<12,2,L17<18,3,L17<24,4,L17<=30,5)} -> 5

Sheet Arquitectura
C1: Frente evaluación | D1: Componente | E1: Criterio | F1: Respuesta/Indicador | G1: Máximo de puntos a evaluar | H1: NAE | I1: WAVENET | J1: ORACLE | K1: HITSS | L1: BLIPBLIP | M1: LARAIGO | N1: FONYOU | O1: SIXBELL | P1: PRONÓSTICA
B2: 1 | C2: Estándares - Arquitectura e ingeniería | D2: Propuesta técnica | E2: Una descripción de porque su solución se ajusta al negocio necesario para el operador y su experiencia en cumplir este tipo de requerimientos. | F2: No Cumple (0 puntos) Cumple parcialmente (+1 punto) Cumple totalmente (+1 punto) | G2: 2 | H2: 2 | I2: 2 | J2: 2 | K2: 1 | L2: 0 | M2: 2 | N2: 2 | O2: 1 | P2: 2
B3: 2 | C3: Estándares - Arquitectura e ingeniería | D3: Propuesta técnica | E3: Descripción / diagrama que muestre la arquitectura de solución propuesta y el mapa lógico entre la arquitectura propuesta y la arquitectura conceptual del Operador. | F3: No Cumple (0 puntos) Cumple parcialmente (+1 punto) Cumple totalmente (+1 punto) | G3: 2 | H3: 2 | I3: 2 | J3: 2 | K3: 1 | L3: 0 | M3: 2 | N3: 2 | O3: 0 | P3: 2
B4: 3 | C4: Estándares - Arquitectura e ingeniería | D4: Propuesta técnica | E4: Descripción y explicación de la arquitectura propuesta incluyendo: 1. Anexo Técnico 2. Arquitectura de hardware y software (TO-BE y en caso de requerir transiciones también deben estar incluidas estas arquitecturas) | F4: No Cumple (0 puntos) Cumple parcialmente (+1 punto) Cumple totalmente (+1 punto) | G4: 2 | H4: 2 | I4: 0 | J4: 2 | K4: 1 | L4: 0 | M4: 2 | N4: 2 | O4: 0 | P4: 1
B5: 4 | C5: Estándares - Arquitectura e ingeniería | D5: Propuesta técnica | E5: Descripción de la funcionalidad de cada componente de la solución, que demuestre en la propuesta la implementación de una arquitectura modular y desacoplada. | F5: No Cumple (0 puntos) Cumple parcialmente (+1 punto) Cumple totalmente (+1 punto) | G5: 2 | H5: 2 | I5: 2 | J5: 2 | K5: 1 | L5: 0 | M5: 2 | N5: 2 | O5: 1 | P5: 1
B6: 5 | C6: Estándares - Arquitectura e ingeniería | D6: Propuesta técnica | E6: Se debe proveer a Claro con un diagrama y documento que permita conocer el modelo de integración de la red de datos en la que estará instalado el sistema con la red de Claro. Este documento será revisado por el personal del departamento de redes de claro Colombia | F6: No Cumple (0 puntos) Cumple parcialmente (+1 punto) Cumple totalmente (+1 punto) | G6: 2 | H6: 2 | I6: 2 | J6: 2 | K6: 0 | L6: 0 | M6: 2 | N6: 1 | O6: 1 | P6: 1
B7: 6 | C7: Estándares - Arquitectura e ingeniería | D7: Propuesta técnica | E7: Compromiso del vendedor para dar soporte local y/o regional, de ser necesario | F7: No Cumple (0 puntos) Cumple parcialmente (+1 punto) Cumple totalmente (+1 punto) | G7: 2 | H7: 2 | I7: 2 | J7: 2 | K7: 2 | L7: 0 | M7: 2 | N7: 2 | O7: 1 | P7: 2
B8: 7 | C8: Estándares - Arquitectura e ingeniería | D8: Propuesta técnica | E8: El Proveedor debe comprobar implementaciones exitosas en empresas de telefonía demostrando la capacidad del producto en operadores de diferentes tamaños. | F8: No Cumple (0 puntos) Cumple parcialmente (+1 punto) Cumple totalmente (+1 punto) | G8: 2 | H8: 2 | I8: 2 | J8: 2 | K8: 0 | L8: 0 | M8: 2 | N8: 2 | O8: 0 | P8: 1
B9: 8 | C9: Estándares - Arquitectura e ingeniería | D9: Propuesta técnica | E9: El Proveedor deberá incluir referencias de los operadores que actualmente se encuentran utilizando su solución, indicando el perfil del operador y los volúmenes manejados. | F9: No Cumple (0 puntos) Cumple parcialmente (+1 punto) Cumple totalmente (+1 punto) | G9: 2 | H9: 2 | I9: 2 | J9: 2 | K9: 0 | L9: 0 | M9: 2 | N9: 1 | O9: 0 | P9: 1
B10: 9 | C10: Estándares - Arquitectura e ingeniería | D10: Propuesta técnica | E10: El Proveedor deberá presentar las certificaciones con que cuente llámese: ISO, CMMI a fin de que se tenga una idea de los procesos de control para el despliegue y soporte del sistema. | F10: No Cumple (0 puntos) Cumple parcialmente (+1 punto) Cumple totalmente (+1 punto) | G10: 2 | H10: 1 | I10: 2 | J10: 2 | K10: 0 | L10: 0 | M10: 1 | N10: 1 | O10: 0 | P10: 1
B11: 10 | C11: Estándares - Arquitectura e ingeniería | D11: Propuesta técnica | E11: El Proveedor deberá acreditar que aplica una metodología de desarrollo con altos estándares de calidad que le permitirán a la empresa contar con una solución probada, creada y diseñada con políticas de ingeniería de software, procesos de pruebas unitarias, procesos de prueba de integración y que cuente con una metodología de implantación. | F11: No Cumple (0 puntos) Cumple parcialmente (+1 punto) Cumple totalmente (+1 punto) | G11: 2 | H11: 2 | I11: 2 | J11: 2 | K11: 2 | L11: 0 | M11: 1 | N11: 1 | O11: 0 | P11: 2
B12: 11 | C12: Estándares - Arquitectura e ingeniería | D12: Propuesta técnica | E12: El Proveedor deberá dar cumplimiento estricto a la confidencialidad de la información suministrada durante el proceso de invitación, contratación e implementación. | F12: No Cumple (0 puntos) Cumple parcialmente (+1 punto) Cumple totalmente (+1 punto) | G12: 2 | H12: 1 | I12: 2 | J12: 2 | K12: 2 | L12: 0 | M12: 1 | N12: 2 | O12: 0 | P12: 2
B13: 12 | C13: Estándares - Arquitectura e ingeniería | D13: Propuesta técnica | E13: El licitador deberá enviar un plan de proyecto detallado claramente para identificar todas las actividades más importantes y milestones. | F13: No Cumple (0 puntos) Cumple parcialmente (+1 punto) Cumple totalmente (+1 punto) | G13: 2 | H13: 2 | I13: 2 | J13: 2 | K13: 1 | L13: 0 | M13: 2 | N13: 2 | O13: 0 | P13: 2
... B268: 267 | C268: Operación y Soporte | D268: Equipo de trabajo propuesto | E268: Una vez asignado el proyecto, de llegarse a comprobar que cualquiera de la información proporcionada no corresponde a la realidad, se podrá considerar este hecho como justa causal para la finalización del contrato por parte de CLARO, dando lugar a las sanciones o multas referidas en el contrato. | F268: No Cumple (0 puntos) Cumple parcialmente (+1 punto) Cumple totalmente (+1 punto) | G268: 2 | H268: 0 | I268: 0 | J268: 0 | K268: 0 | L268: 0 | M268: 2 | N268: 1 | O268: 2 | P268: 0
F269: Total puntos | G269: =SUM(G2:G268) -> 534 | H269: =SUM(H2:H268) -> 397 | I269: =SUM(I2:I268) -> 335 | J269: =SUM(J2:J268) -> 300 | K269: =SUM(K2:K268) -> 45 | L269: =SUM(L2:L268) -> 8 | M269: =SUM(M2:M268) -> 484 | N269: =SUM(N2:N268) -> 224 | ... P269: =SUM(P2:P268) -> 202.98923
F270: Ponderado escala | G270: =G269/5 -> 106.8 | H270: {=_xlfn.IFS(H269=0,0,H269<100,1,H269<200,2,H269<300,3,H269<400,4,H269<=534,5)} -> 4 | I270: {=_xlfn.IFS(I269=0,0,I269<100,1,I269<200,2,I269<300,3,I269<400,4,I269<=534,5)} -> 4 | J270: {=_xlfn.IFS(J269=0,0,J269<100,1,J269<200,2,J269<300,3,J269<400,4,J269<=534,5)} -> 4 | K270: {=_xlfn.IFS(K269=0,0,K269<100,1,K269<200,2,K269<300,3,K269<400,4,K269<=534,5)} -> 1 | L270: {=_xlfn.IFS(L269=0,0,L269<100,1,L269<200,2,L269<300,3,L269<400,4,L269<=534,5)} -> 1 | M270: {=_xlfn.IFS(M269=0,0,M269<100,1,M269<200,2,M269<300,3,M269<400,4,M269<=534,5)} -> 5 | N270: {=_xlfn.IFS(N269=0,0,N269<100,1,N269<200,2,N269<300,3,N269<400,4,N269<=534,5)} -> 3 | O270: {=_xlfn.IFS(O269=0,0,O269<100,1,O269<200,2,O269<300,3,O269<400,4,O269<=534,5)} -> 3 | P270: {=_xlfn.IFS(P269=0,0,P269<100,1,P269<200,2,P269<300,3,P269<400,4,P269<=534,5)} -> 3

Sheet Seguridad
B1: Criterio | C1: Respuesta/Indicador | D1: Máximo de puntos a evaluar | E1: NAE | F1: WAVENET | G1: ORACLE | H1: HITSS | I1: BLIPBLIP | J1: LARAIGO | K1: FONYOU | L1: SIXBELL | M1: PRONÓSTICA
B2: ¿La herramienta permite hacer la integración con los mecanismos dispuestos por la organización para ingresar con Múltiple Factor de Autenticación? | C2: No Cumple (0 puntos) Cumple parcialmente (+1 punto) Cumple totalmente (+1 punto) | D2: 2 | E2: 2 | F2: 0 | G2: 2 | H2: 0 | I2: 0 | J2: 0 | K2: 0 | L2: 0 | M2: 0
B3: Se deben definir las tablas de retención sobre las transacciones que se almacenan. | C3: No Cumple (0 puntos) Cumple parcialmente (+1 punto) Cumple totalmente (+1 punto) | D3: 2 | E3: 2 | F3: 0 | G3: 2 | H3: 0 | I3: 0 | J3: 0 | K3: 0 | L3: 0 | M3: 2
B4: ¿Los registros de las transacciones se almacenarán solamente en los Audit logs del SIEM de Claro o también de forma local? | C4: No Cumple (0 puntos) Cumple parcialmente (+1 punto) Cumple totalmente (+1 punto) | D4: 2 | E4: 2 | F4: 0 | G4: 2 | H4: 0 | I4: 0 | J4: 2 | K4: 0 | L4: 0 | M4: 2
B5: ¿Se generarán copias de seguridad externas de las transacciones generadas? - si es así, ¿Cómo se aseguran estas copias de seguridad para garantizar la confidencialidad, integridad y disponibilidad de la información? | C5: No Cumple (0 puntos) Cumple parcialmente (+1 punto) Cumple totalmente (+1 punto) | D5: 2 | E5: 2 | F5: 0 | G5: 2 | H5: 0 | I5: 0 | J5: 0 | K5: 2 | L5: 0 | M5: 2
B6: Para la integración con los servicios de Claro, solo se deben aceptar puertos y protocolos seguros de acuerdo con los parámetros de seguridad definidos (se debe seguir las Líneas base de seguridad (LBS) definidas por la organización.). | C6: No Cumple (0 puntos) Cumple parcialmente (+1 punto) Cumple totalmente (+1 punto) | D6: 2 | E6: 2 | F6: 0 | G6: 2 | H6: 0 | I6: 0 | J6: 0 | K6: 0 | L6: 0 | M6: 2
B7: Para la generación y cumplimiento de contraseñas se debe seguir el estándar de seguridad de la información- LBS contraseñas. | C7: No Cumple (0 puntos) Cumple parcialmente (+1 punto) Cumple totalmente (+1 punto) | D7: 2 | E7: 2 | F7: 0 | G7: 2 | H7: 0 | I7: 0 | J7: 0 | K7: 0 | L7: 0 | M7: 0
B8: Se debe definir un análisis de riesgos para identificar los riesgos inherentes y residuales en cuanto a la integración de la herramienta con los servicios de Claro Colombia. | C8: No Cumple (0 puntos) Cumple parcialmente (+1 punto) Cumple totalmente (+1 punto) | D8: 2 | E8: 2 | F8: 0 | G8: 2 | H8: 0 | I8: 0 | J8: 0 | K8: 0 | L8: 0 | M8: 0
B9: ¿Cuál es la metodología y arquitectura que se llevará a cabo para la creación, manejo, administración e intercambio de llaves criptográficas? | C9: No Cumple (0 puntos) Cumple parcialmente (+1 punto) Cumple totalmente (+1 punto) | D9: 2 | E9: 2 | F9: 0 | G9: 2 | H9: 0 | I9: 0 | J9: 0 | K9: 0 | L9: 0 | M9: 0
B10: ¿La herramienta viene con usuarios definidos por aplicación? Si es así, ¿Cómo será el manejo de estos usuarios? ¿Quién tendrá la custodia de administración de estos usuarios? | C10: No Cumple (0 puntos) Cumple parcialmente (+1 punto) Cumple totalmente (+1 punto) | D10: 2 | E10: 2 | F10: 0 | G10: 2 | H10: 0 | I10: 0 | J10: 0 | K10: 0 | L10: 0 | M10: 0
B11: La solución debe tener la capacidad de auditoría y generar registros de transacciones, con un identificador que permita clasificar el tipo de transacción, el origen, timestamp, entre otros, y la transacción debe ser recuperable (almacenada) por un tiempo X que define el área de negocio de Claro Colombia. Las LBS indican que se deben mantener registros de por lo menos 3 meses de manera inmediata y 1 año en reposo. Este periodo debe ser configurable | C11: No Cumple (0 puntos) Cumple parcialmente (+1 punto) Cumple totalmente (+1 punto) | D11: 2 | E11: 2 | F11: 0 | G11: 2 | H11: 0 | I11: 0 | J11: 0 | K11: 2 | L11: 0 | M11: 0
B12: Los parámetros de seguridad deben ser configurables para toda la plataforma. Todos los métodos deben soportar SSL o cifrado compatible con las plataformas de CLARO. | C12: No Cumple (0 puntos) Cumple parcialmente (+1 punto) Cumple totalmente (+1 punto) | D12: 2 | E12: 2 | F12: 0 | G12: 2 | H12: 0 | I12: 0 | J12: 0 | K12: 2 | L12: 0 | M12: 0
B13: Los passwords deben poder ser cambiados en toda la plataforma de forma simple (ej: rutinas sobre los blades). Los usuarios deben tener distintos niveles de acceso según sus actividades, manejo de roles y perfiles. Debe integrarse con el OIM de seguridad informática para la centralización tanto de usuarios como perfiles de usuarios y contemplar la complejidad de contraseñas. | C13: No Cumple (0 puntos) Cumple parcialmente (+1 punto) Cumple totalmente (+1 punto) | D13: 2 | E13: 2 | F13: 0 | G13: 2 | H13: 0 | I13: 0 | J13: 0 | K13: 0 | L13: 0 | M13: 0
... B21: La solución debería incluir compatibilidad en integración con SAML o SSO? | C21: No Cumple (0 puntos) Cumple parcialmente (+1 punto) Cumple totalmente (+1 punto) | D21: 2 | E21: 2 | F21: 0 | G21: 2 | H21: 0 | I21: 0 | J21: 0 | K21: 0 | L21: 0 | M21: 0
C22: Total puntos | D22: =SUM(D2:D21) -> 40 | E22: =SUM(E2:E21) -> 40 | F22: =SUM(F2:F21) -> 0 | G22: =SUM(G2:G21) -> 40 | H22: =SUM(H2:H21) -> 0 | I22: =SUM(I2:I21) -> 0 | J22: =SUM(J2:J21) -> 2 | K22: =SUM(K2:K21) -> 11 | ... M22: =SUM(M2:M21) -> 13
C23: Ponderado escala | D23: =D22/5 -> 8 | E23: {=_xlfn.IFS(E22=0,0,E22<8,1,E22<16,2,E22<24,3,E22<32,4,E22<=40,5)} -> 5 | F23: {=_xlfn.IFS(F22=0,0,F22<8,1,F22<16,2,F22<24,3,F22<32,4,F22<=40,5)} -> 0 | G23: {=_xlfn.IFS(G22=0,0,G22<8,1,G22<16,2,G22<24,3,G22<32,4,G22<=40,5)} -> 5 | H23: {=_xlfn.IFS(H22=0,0,H22<8,1,H22<16,2,H22<24,3,H22<32,4,H22<=40,5)} -> 0 | I23: {=_xlfn.IFS(I22=0,0,I22<8,1,I22<16,2,I22<24,3,I22<32,4,I22<=40,5)} -> 0 | J23: {=_xlfn.IFS(J22=0,0,J22<8,1,J22<16,2,J22<24,3,J22<32,4,J22<=40,5)} -> 1 | K23: {=_xlfn.IFS(K22=0,0,K22<8,1,K22<16,2,K22<24,3,K22<32,4,K22<=40,5)} -> 2 | L23: {=_xlfn.IFS(L22=0,0,L22<8,1,L22<16,2,L22<24,3,L22<32,4,L22<=40,5)} -> 0 | M23: {=_xlfn.IFS(M22=0,0,M22<8,1,M22<16,2,M22<24,3,M22<32,4,M22<=40,5)} -> 2

Sheet Riesgo
B1: Criterio | C1: Respuesta/Indicador | D1: Máximo de puntos a evaluar | E1: NAE | F1: WAVENET | G1: ORACLE | H1: HITSS | I1: BLIPBLIP | J1: LARAIGO | K1: FONYOU | L1: SIXBELL | M1: PRONÓSTICA
B2: ¿Tiene experiencia previa en implementación de soluciones similares (IA)? | C2: No Cumple (0 puntos) Cumple parcialmente (+1 punto) Cumple totalmente (+1 punto) | D2: 2 | E2: 2 | F2: 2 | G2: 2 | H2: 2 | I2: 2 | J2: 2 | K2: 2 | L2: 2 | M2: 2
B3: ¿Cumple con los tiempos solicitados de implementación y puesta en marcha? | C3: No Cumple (0 puntos) Cumple parcialmente (+1 punto) Cumple totalmente (+1 punto) | D3: 2 | E3: 0 | F3: 2 | G3: 2 | H3: 0 | I3: 0 | J3: 2 | K3: 1 | L3: 2 | M3: 1
B4: ¿Cuenta con referencias verificables de clientes? | C4: No Cumple (0 puntos) Cumple parcialmente (+1 punto) Cumple totalmente (+1 punto) | D4: 2 | E4: 2 | F4: 2 | G4: 2 | H4: 2 | I4: 2 | J4: 2 | K4: 2 | L4: 2 | M4: 2
B5: ¿Tiene capacidades de soporte y acompañamiento post-implementación? | C5: No Cumple (0 puntos) Cumple parcialmente (+1 punto) Cumple totalmente (+1 punto) | D5: 2 | E5: 2 | F5: 2 | G5: 2 | H5: 1 | I5: 2 | J5: 2 | K5: 2 | L5: 2 | M5: 2
B6: ¿Cuenta con certificaciones del proveedor cloud o tecnologías usadas? | C6: No Cumple (0 puntos) Cumple parcialmente (+1 punto) Cumple totalmente (+1 punto) | D6: 2 | E6: 2 | F6: 1 | G6: 2 | H6: 1 | I6: 2 | J6: 2 | K6: 1 | L6: 1 | M6: 1
B7: ¿Puede demostrar mejoras cuantificables en proyectos anteriores? | C7: No Cumple (0 puntos) Cumple parcialmente (+1 punto) Cumple totalmente (+1 punto) | D7: 2 | E7: 2 | F7: 2 | G7: 2 | H7: 1 | I7: 2 | J7: 2 | K7: 2 | L7: 2 | M7: 1
C8: Total puntos | D8: =SUM(D2:D7) -> 12 | E8: =SUM(E2:E7) -> 10 | F8: =SUM(F2:F7) -> 11 | G8: =SUM(G2:G7) -> 12 | H8: =SUM(H2:H7) -> 7 | I8: =SUM(I2:I7) -> 10 | J8: =SUM(J2:J7) -> 12 | K8: =SUM(K2:K7) -> 10 | ... M8: =SUM(M2:M7) -> 9
C9: Ponderado escala | D9: =D8/5 -> 2.4 | E9: {=_xlfn.IFS(E8<2.5,1,E8<5,2,E8<8,3,E8<10.5,4,E8<=12,5)} -> 4 | F9: {=_xlfn.IFS(F8<2.5,1,F8<5,2,F8<8,3,F8<10.5,4,F8<=12,5)} -> 5 | G9: {=_xlfn.IFS(G8<2.5,1,G8<5,2,G8<8,3,G8<10.5,4,G8<=12,5)} -> 5 | H9: {=_xlfn.IFS(H8<2.5,1,H8<5,2,H8<8,3,H8<10.5,4,H8<=12,5)} -> 3 | I9: {=_xlfn.IFS(I8<2.5,1,I8<5,2,I8<8,3,I8<10.5,4,I8<=12,5)} -> 4 | J9: {=_xlfn.IFS(J8<2.5,1,J8<5,2,J8<8,3,J8<10.5,4,J8<=12,5)} -> 5 | K9: {=_xlfn.IFS(K8<2.5,1,K8<5,2,K8<8,3,K8<10.5,4,K8<=12,5)} -> 4 | L9: {=_xlfn.IFS(L8<2.5,1,L8<5,2,L8<8,3,L8<10.5,4,L8<=12,5)} -> 5 | M9: {=_xlfn.IFS(M8<2.5,1,M8<5,2,M8<8,3,M8<10.5,4,M8<=12,5)} -> 4

Sheet Resumen
B2: PESO | C2: CRITERIOS | D2: OFERTANTE
D3: NAE | E3: WAVENET | F3: ORACLE | G3: HITSS | H3: BLIPBLIP | I3: LARAIGO | J3: FONYOU | K3: SIXBELL | L3: PRONÓSTICA
B4: 0.3 | C4: Alcance funcional | D4: =Funcional!E13 -> 5 | E4: =Funcional!F13 -> 3 | F4: =Funcional!G13 -> 5 | G4: =Funcional!H13 -> 4 | H4: =Funcional!I13 -> 3 | I4: =Funcional!J13 -> 4 | J4: =Funcional!K13 -> 4 | K4: =Funcional!L13 -> 3 | L4: =Funcional!M13 -> 3
B5: 0.3 | C5: Alcance técnico | D5: =Técnico!E31 -> 3 | E5: =Técnico!F31 -> 3 | F5: =Técnico!G31 -> 5 | G5: =Técnico!H31 -> 3 | H5: =Técnico!I31 -> 2 | I5: =Técnico!J31 -> 3 | J5: =Técnico!K31 -> 2 | K5: =Técnico!L31 -> 4 | L5: =Técnico!M31 -> 3
B6: 0.15 | C6: Arquitectura | D6: {=Arquitectura!H270:P270} -> 4 | E6: 4 | F6: 4 | G6: 1 | H6: 1 | I6: 5 | J6: 3 | K6: 3 | L6: 3
B7: 0.1 | C7: Seguridad, control riesgos | D7: =Seguridad!E23 -> 5 | E7: =Seguridad!F23 -> 0 | F7: =Seguridad!G23 -> 5 | G7: =Seguridad!H23 -> 0 | H7: =Seguridad!I23 -> 0 | I7: =Seguridad!J23 -> 1 | J7: =Seguridad!K23 -> 2 | K7: =Seguridad!L23 -> 0 | L7: =Seguridad!M23 -> 2
B8: 0.15 | C8: Riesgos del proyecto | D8: =Riesgo!E9 -> 4 | E8: =Riesgo!F9 -> 5 | F8: =Riesgo!G9 -> 5 | G8: =Riesgo!H9 -> 3 | H8: =Riesgo!I9 -> 4 | I8: =Riesgo!J9 -> 5 | J8: =Riesgo!K9 -> 4 | K8: =Riesgo!L9 -> 5 | L8: =Riesgo!M9 -> 4
B9: 1 | C9: Oferta | D9: =SUMPRODUCT($B$4:$B$8,D4:D8) -> 4.1 | E9: =SUMPRODUCT($B$4:$B$8,E4:E8) -> 3.15 | F9: =SUMPRODUCT($B$4:$B$8,F4:F8) -> 4.85 | G9: =SUMPRODUCT($B$4:$B$8,G4:G8) -> 2.7 | H9: =SUMPRODUCT($B$4:$B$8,H4:H8) -> 2.25 | I9: =SUMPRODUCT($B$4:$B$8,I4:I8) -> 3.7 | J9: =SUMPRODUCT($B$4:$B$8,J4:J8) -> 3.05 | K9: =SUMPRODUCT($B$4:$B$8,K4:K8) -> 3.3 | L9: =SUMPRODUCT($B$4:$B$8,L4:L8) -> 3.05
